doc/soft-moe-layer.jpeg
soft_mixture_of_experts/__init__.py
soft_mixture_of_experts/multi_expert.py
soft_mixture_of_experts/soft_moe.py
soft_mixture_of_experts/transformer.py
soft_mixture_of_experts/vit.py
soft_mixture_of_experts-0.2.0.dist-info/LICENSE
soft_mixture_of_experts-0.2.0.dist-info/METADATA
soft_mixture_of_experts-0.2.0.dist-info/WHEEL
soft_mixture_of_experts-0.2.0.dist-info/top_level.txt
soft_mixture_of_experts-0.2.0.dist-info/RECORD
