Metadata-Version: 2.1
Name: soft-mixture-of-experts
Version: 0.2.0
Summary: soft-mixture-of-experts
Author-email: Frank Odom <frank.odom.iii@mgmail.com>
License: MIT
Classifier: Programming Language :: Python :: 3
Requires-Python: >=3.8
License-File: LICENSE
Requires-Dist: torch >=1.8
Requires-Dist: einops
Provides-Extra: test
Requires-Dist: black ; extra == 'test'
Requires-Dist: mypy ; extra == 'test'
Requires-Dist: pre-commit ; extra == 'test'
Requires-Dist: pytest ; extra == 'test'
Requires-Dist: pytest-cov ; extra == 'test'
Requires-Dist: ruff ; extra == 'test'
